hanotify
setup.py
hanotify.egg-info/PKG-INFO
hanotify.egg-info/SOURCES.txt
hanotify.egg-info/dependency_links.txt
hanotify.egg-info/requires.txt
hanotify.egg-info/top_level.txt
hanotifylib/__init__.py
hanotifylib/report.py
hanotifylib/watch.py