Metadata-Version: 1.0
Name: hanotify
Version: 0.1.0
Summary: An email notification tool for hockey app crash reports
Home-page: UNKNOWN
Author: Benjamin Wallis
Author-email: ben.nat.wallis@gmail.com
License: BSD
Keywords: hockeyapp crash hanotify
Platform: UNKNOWN
